emitter_tools/__init__.py
emitter_tools/py.typed
babichjacob_emitter_tools-0.1.2.dist-info/METADATA
babichjacob_emitter_tools-0.1.2.dist-info/WHEEL
babichjacob_emitter_tools-0.1.2.dist-info/RECORD
