Metadata-Version: 2.1
Name: babichjacob-emitter-tools
Version: 0.1.2
Summary: Tools for working with event emitters
Home-page: https://github.com/babichjacob/python-emitter-tools
License: MIT
Author: J or Jacob Babich
Author-email: jacobbabichpublic+git@gmail.com
Requires-Python: >=3.10
Classifier: License :: OSI Approved :: MIT License
Classifier: Programming Language :: Python :: 3
Classifier: Programming Language :: Python :: 3.10
Classifier: Programming Language :: Python :: 3.11
Requires-Dist: babichjacob-emitter (>=0.1.1,<0.2.0)
Requires-Dist: babichjacob-option-and-result (>=0.1.2,<0.2.0)
Requires-Dist: babichjacob-store (>=0.2.0,<0.3.0)
Project-URL: Repository, https://github.com/babichjacob/python-emitter-tools
